ftd/__init__.py
ftd/module/__init__.py
ftd/module/custom_layers.py
ftd/module/detector.py
ftd/module/loss.py
ftd/module/shufflenetv2.py
ftdcherub-0.5.dist-info/METADATA
ftdcherub-0.5.dist-info/WHEEL
ftdcherub-0.5.dist-info/top_level.txt
ftdcherub-0.5.dist-info/RECORD
