Metadata-Version: 2.1
Name: ftdcherub
Version: 0.5
Summary: Just use for myself
Author: Cherub
Author-email: zhaungxinwei@gmail.com
Classifier: Programming Language :: Python :: 3
Classifier: License :: OSI Approved :: MIT License
Classifier: Operating System :: OS Independent
Requires-Python: >=3.6
